nomad_camels_driver_demo_source_measure_unit/__init__.py
nomad_camels_driver_demo_source_measure_unit/demo_source_measure_unit.py
nomad_camels_driver_demo_source_measure_unit/demo_source_measure_unit_ophyd.py
nomad_camels_driver_demo_source_measure_unit-0.1.7.dist-info/licenses/LICENSE.txt
nomad_camels_driver_demo_source_measure_unit-0.1.7.dist-info/METADATA
nomad_camels_driver_demo_source_measure_unit-0.1.7.dist-info/WHEEL
nomad_camels_driver_demo_source_measure_unit-0.1.7.dist-info/top_level.txt
nomad_camels_driver_demo_source_measure_unit-0.1.7.dist-info/RECORD
